setup.py
MeORM.egg-info/PKG-INFO
MeORM.egg-info/SOURCES.txt
MeORM.egg-info/dependency_links.txt
MeORM.egg-info/top_level.txt
morm/__init__.py
morm/config/__init__.py
morm/config/connect.template.yaml
morm/config/dao_gen.yaml
morm/core/__init__.py
morm/core/_gen.py
morm/core/context.py
morm/core/dbhelper.py
morm/core/decorator.py
test/__init__.py
test/test.py
test/test11.py
test/test2.py