Metadata-Version: 1.0
Name: MeORM
Version: 1.47
Summary: orm框架
Home-page: https://github.com/Blackstone1204
Author: blackstone
Author-email: 971406187@qq.com
License: UNKNOWN
Platform: UNKNOWN
